neatbio/__init__.py
neatbio/neatbio.py
neatbio/sequtils/__init__.py
neatbio/sequtils/sequtils.py
neatbio-0.0.1.dist-info/LICENSE
neatbio-0.0.1.dist-info/WHEEL
neatbio-0.0.1.dist-info/METADATA
neatbio-0.0.1.dist-info/RECORD
