Metadata-Version: 2.1
Name: neatbio
Version: 0.0.1
Summary: NeatBio - a simple Yet Another BioInformatics Library for DNA Sequence
Home-page: https://github.com/Jcharis/neatbio
License: MIT
Keywords: neatbio,biopython,jcharistech,biotite,BioInformatics,Sequence Analysis,DNA and RNA,scikit-bio,protein synthesis
Author: Jesse E.Agbe(JCharis)
Author-email: jcharistech@gmail.com
Requires-Python: >=3.3,<4.0
Classifier: License :: OSI Approved :: MIT License
Classifier: Operating System :: OS Independent
Classifier: Programming Language :: Python :: 3
Classifier: Programming Language :: Python :: 3.4
Classifier: Programming Language :: Python :: 3.5
Classifier: Programming Language :: Python :: 3.6
Classifier: Programming Language :: Python :: 3.7
Classifier: Programming Language :: Python :: 3.8
Project-URL: Repository, https://github.com/Jcharis/neatbio
